{
  "title": "Learning Resources",
  "path": "_learning",
  "page": 19,
  "value": [
    {
      "path": "_learning/courses/microsoft-learn-github-actions-ci.md",
      "title": "Build continuous integration (CI) workflows by using GitHub Actions",
      "excerpt": "Learn how to create workflows that enable you to use Continuous Integration (CI) for your projects.",
      "sourceUrl": "https://smartableai.github.io/microsoft-azure/api/learning/courses/microsoft-learn-github-actions-ci/index.json",
      "webUrl": "https://docs.microsoft.com/en-us/learn/modules/github-actions-ci/",
      "length": "PT55M",
      "ratings": {
        "count": 205,
        "average": 4.721951
      },
      "provider": {
        "name": "Microsoft Learn",
        "domain": "microsoft.com",
        "images": [
          {
            "url": "https://smartableai.github.io/microsoft-azure/assets/images/organizations/microsoft.com-50x50.jpg",
            "width": 50,
            "height": 50,
            "isCached": false
          }
        ]
      },
      "levels": [
        "Beginner"
      ],
      "heat": 51,
      "images": [
        {
          "url": "https://docs.microsoft.com/learn/achievements/github/github-actions-ci-social.png",
          "width": 640,
          "height": 320,
          "isCached": true
        }
      ],
      "content": "\r\n",
      "type": "course",
      "price": "Free",
      "topics": [
        "Azure",
        "Integration"
      ]
    },
    {
      "path": "_learning/courses/microsoft-learn-ha-application-storage-with-grs.md",
      "title": "Make your application storage highly available with read-access geo-redundant storage",
      "excerpt": "In this module, you learn how to make your application storage highly available by ensuring that you can fail over resources if there's an Azure region failure.",
      "sourceUrl": "https://smartableai.github.io/microsoft-azure/api/learning/courses/microsoft-learn-ha-application-storage-with-grs/index.json",
      "webUrl": "https://docs.microsoft.com/en-us/learn/modules/ha-application-storage-with-grs/",
      "length": "PT34M",
      "ratings": {
        "count": 1461,
        "average": 4.486653
      },
      "provider": {
        "name": "Microsoft Learn",
        "domain": "microsoft.com",
        "images": [
          {
            "url": "https://smartableai.github.io/microsoft-azure/assets/images/organizations/microsoft.com-50x50.jpg",
            "width": 50,
            "height": 50,
            "isCached": false
          }
        ]
      },
      "levels": [
        "Beginner"
      ],
      "heat": 51,
      "images": [
        {
          "url": "https://docs.microsoft.com/learn/achievements/ha-application-storage-with-grs-social.png",
          "width": 800,
          "height": 400,
          "isCached": true
        }
      ],
      "content": "\r\n",
      "type": "course",
      "price": "Free",
      "topics": [
        "Azure",
        "Storage"
      ]
    },
    {
      "path": "_learning/courses/microsoft-learn-host-domain-azure-dns.md",
      "title": "Host your domain on Azure DNS",
      "excerpt": "Learn how to host your domain on Azure DNS.",
      "sourceUrl": "https://smartableai.github.io/microsoft-azure/api/learning/courses/microsoft-learn-host-domain-azure-dns/index.json",
      "webUrl": "https://docs.microsoft.com/en-us/learn/modules/host-domain-azure-dns/",
      "length": "PT43M",
      "ratings": {
        "count": 2777,
        "average": 4.8203096
      },
      "provider": {
        "name": "Microsoft Learn",
        "domain": "microsoft.com",
        "images": [
          {
            "url": "https://smartableai.github.io/microsoft-azure/assets/images/organizations/microsoft.com-50x50.jpg",
            "width": 50,
            "height": 50,
            "isCached": false
          }
        ]
      },
      "levels": [
        "Beginner"
      ],
      "heat": 51,
      "images": [
        {
          "url": "https://docs.microsoft.com/learn/achievements/host-domain-azure-dns-social.png",
          "width": 800,
          "height": 400,
          "isCached": true
        }
      ],
      "content": "\r\n",
      "type": "course",
      "price": "Free",
      "topics": [
        "Azure",
        "Networking"
      ]
    },
    {
      "path": "_learning/courses/microsoft-learn-identify-threats-with-azure-security-center.md",
      "title": "Identify security threats with Azure Security Center",
      "excerpt": "Master securing your Azure workloads with Azure Security Center. In this module, you’ll discover how to detect and respond to threats with Azure Security Center.",
      "sourceUrl": "https://smartableai.github.io/microsoft-azure/api/learning/courses/microsoft-learn-identify-threats-with-azure-security-center/index.json",
      "webUrl": "https://docs.microsoft.com/en-us/learn/modules/identify-threats-with-azure-security-center/",
      "length": "PT43M",
      "ratings": {
        "count": 833,
        "average": 4.6938777
      },
      "provider": {
        "name": "Microsoft Learn",
        "domain": "microsoft.com",
        "images": [
          {
            "url": "https://smartableai.github.io/microsoft-azure/assets/images/organizations/microsoft.com-50x50.jpg",
            "width": 50,
            "height": 50,
            "isCached": false
          }
        ]
      },
      "levels": [
        "Beginner"
      ],
      "heat": 51,
      "images": [
        {
          "url": "https://docs.microsoft.com/learn/achievements/identify-threats-with-azure-security-center-social.png",
          "width": 800,
          "height": 400,
          "isCached": true
        }
      ],
      "content": "\r\n",
      "type": "course",
      "price": "Free",
      "topics": [
        "Azure",
        "Security"
      ]
    },
    {
      "path": "_learning/courses/microsoft-learn-improve-reliability-failure.md",
      "title": "Improve your reliability with modern operations practices: Learning from failure",
      "excerpt": "Learn about post-incident reviews, a practice necessary to help you sustainably achieve the appropriate level of reliability in your systems, services, and products.",
      "sourceUrl": "https://smartableai.github.io/microsoft-azure/api/learning/courses/microsoft-learn-improve-reliability-failure/index.json",
      "webUrl": "https://docs.microsoft.com/en-us/learn/modules/improve-reliability-failure/",
      "length": "PT34M",
      "ratings": {
        "count": 190,
        "average": 4.6473684
      },
      "provider": {
        "name": "Microsoft Learn",
        "domain": "microsoft.com",
        "images": [
          {
            "url": "https://smartableai.github.io/microsoft-azure/assets/images/organizations/microsoft.com-50x50.jpg",
            "width": 50,
            "height": 50,
            "isCached": false
          }
        ]
      },
      "levels": [
        "Beginner"
      ],
      "heat": 51,
      "images": [
        {
          "url": "https://docs.microsoft.com/learn/achievements/improve-reliability-failure-social.png",
          "width": 640,
          "height": 320,
          "isCached": true
        }
      ],
      "content": "\r\n",
      "type": "course",
      "price": "Free",
      "topics": [
        "Azure"
      ]
    },
    {
      "path": "_learning/courses/microsoft-learn-instrument-web-app-code-with-application-insights.md",
      "title": "Instrument server-side web application code with Application Insights",
      "excerpt": "Get full information and custom telemetry about a web app in Application Insights by installing the Application Insights SDK.",
      "sourceUrl": "https://smartableai.github.io/microsoft-azure/api/learning/courses/microsoft-learn-instrument-web-app-code-with-application-insights/index.json",
      "webUrl": "https://docs.microsoft.com/en-us/learn/modules/instrument-web-app-code-with-application-insights/",
      "length": "PT34M",
      "ratings": {
        "count": 398,
        "average": 4.5728645
      },
      "provider": {
        "name": "Microsoft Learn",
        "domain": "microsoft.com",
        "images": [
          {
            "url": "https://smartableai.github.io/microsoft-azure/assets/images/organizations/microsoft.com-50x50.jpg",
            "width": 50,
            "height": 50,
            "isCached": false
          }
        ]
      },
      "levels": [
        "Beginner"
      ],
      "heat": 51,
      "images": [
        {
          "url": "https://docs.microsoft.com/learn/achievements/instrument-web-app-code-with-application-insights-social.png",
          "width": 800,
          "height": 400,
          "isCached": true
        }
      ],
      "content": "\r\n",
      "type": "course",
      "price": "Free",
      "topics": [
        "Azure"
      ]
    },
    {
      "path": "_learning/courses/microsoft-learn-intro-to-azure-machine-learning-service.md",
      "title": "Introduction to the Azure Machine Learning SDK",
      "excerpt": "Azure Machine Learning provides a cloud-based platform for training, deploying, and managing machine learning models.",
      "sourceUrl": "https://smartableai.github.io/microsoft-azure/api/learning/courses/microsoft-learn-intro-to-azure-machine-learning-service/index.json",
      "webUrl": "https://docs.microsoft.com/en-us/learn/modules/intro-to-azure-machine-learning-service/",
      "length": "PT40M",
      "ratings": {
        "count": 2474,
        "average": 4.6253033
      },
      "provider": {
        "name": "Microsoft Learn",
        "domain": "microsoft.com",
        "images": [
          {
            "url": "https://smartableai.github.io/microsoft-azure/assets/images/organizations/microsoft.com-50x50.jpg",
            "width": 50,
            "height": 50,
            "isCached": false
          }
        ]
      },
      "levels": [
        "Beginner"
      ],
      "heat": 51,
      "images": [
        {
          "url": "https://docs.microsoft.com/learn/achievements/intro-to-azure-machine-learning-service-badge-social.png",
          "width": 800,
          "height": 400,
          "isCached": true
        }
      ],
      "content": "\r\n",
      "type": "course",
      "price": "Free",
      "topics": [
        "Azure",
        "AI",
        "Developer tools"
      ]
    },
    {
      "path": "_learning/courses/microsoft-learn-intro-to-azure-sentinel.md",
      "title": "Introduction to Azure Sentinel",
      "excerpt": "Get familiar with Azure Sentinel, a cloud-native, security information and event management (SIEM) service.",
      "sourceUrl": "https://smartableai.github.io/microsoft-azure/api/learning/courses/microsoft-learn-intro-to-azure-sentinel/index.json",
      "webUrl": "https://docs.microsoft.com/en-us/learn/modules/intro-to-azure-sentinel/",
      "length": "PT29M",
      "ratings": {
        "count": 238,
        "average": 4.7352943
      },
      "provider": {
        "name": "Microsoft Learn",
        "domain": "microsoft.com",
        "images": [
          {
            "url": "https://smartableai.github.io/microsoft-azure/assets/images/organizations/microsoft.com-50x50.jpg",
            "width": 50,
            "height": 50,
            "isCached": false
          }
        ]
      },
      "levels": [
        "Beginner"
      ],
      "heat": 51,
      "content": "\r\n",
      "type": "course",
      "price": "Free",
      "topics": [
        "Azure",
        "Security"
      ]
    },
    {
      "path": "_learning/courses/microsoft-learn-intro-to-hpc.md",
      "title": "Introduction to high-performance computing (HPC) on Azure",
      "excerpt": "Discover the services available on Azure for your high-performance computing workloads.",
      "sourceUrl": "https://smartableai.github.io/microsoft-azure/api/learning/courses/microsoft-learn-intro-to-hpc/index.json",
      "webUrl": "https://docs.microsoft.com/en-us/learn/modules/intro-to-hpc/",
      "length": "PT50M",
      "ratings": {
        "count": 1151,
        "average": 4.5838404
      },
      "provider": {
        "name": "Microsoft Learn",
        "domain": "microsoft.com",
        "images": [
          {
            "url": "https://smartableai.github.io/microsoft-azure/assets/images/organizations/microsoft.com-50x50.jpg",
            "width": 50,
            "height": 50,
            "isCached": false
          }
        ]
      },
      "levels": [
        "Beginner"
      ],
      "heat": 51,
      "images": [
        {
          "url": "https://docs.microsoft.com/learn/achievements/intro-to-hpc-social.png",
          "width": 800,
          "height": 400,
          "isCached": true
        }
      ],
      "content": "\r\n",
      "type": "course",
      "price": "Free",
      "topics": [
        "Azure",
        "Compute"
      ]
    },
    {
      "path": "_learning/courses/microsoft-learn-intro-to-java-azure.md",
      "title": "Introduction to Java on Azure",
      "excerpt": "Goal of this module is to welcome you as Java Developers on Azure. In this module, you'll begin to discover the opportunities for Java developers on Azure.",
      "sourceUrl": "https://smartableai.github.io/microsoft-azure/api/learning/courses/microsoft-learn-intro-to-java-azure/index.json",
      "webUrl": "https://docs.microsoft.com/en-us/learn/modules/intro-to-java-azure/",
      "length": "PT37M",
      "ratings": {
        "count": 37,
        "average": 4.810811
      },
      "provider": {
        "name": "Microsoft Learn",
        "domain": "microsoft.com",
        "images": [
          {
            "url": "https://smartableai.github.io/microsoft-azure/assets/images/organizations/microsoft.com-50x50.jpg",
            "width": 50,
            "height": 50,
            "isCached": false
          }
        ]
      },
      "levels": [
        "Beginner"
      ],
      "heat": 51,
      "images": [
        {
          "url": "https://docs.microsoft.com/learn/achievements/generic-badge-social.png",
          "width": 640,
          "height": 320,
          "isCached": true
        }
      ],
      "content": "\r\n",
      "type": "course",
      "price": "Free",
      "topics": [
        "Azure"
      ]
    },
    {
      "path": "_learning/courses/microsoft-learn-introduction-lambda-architecture-iot-solutions.md",
      "title": "Introduction to implementing lambda architecture for IoT solutions",
      "excerpt": "An overview of the concepts and resources behind storage technologies used in IoT applications on Azure. After completing the module, you can determine when to use Blob storage, Data Lake storage, Azure Cosmos DB, and Time Series Insights.",
      "sourceUrl": "https://smartableai.github.io/microsoft-azure/api/learning/courses/microsoft-learn-introduction-lambda-architecture-iot-solutions/index.json",
      "webUrl": "https://docs.microsoft.com/en-us/learn/modules/introduction-lambda-architecture-iot-solutions/",
      "length": "PT28M",
      "ratings": {
        "count": 473,
        "average": 4.630021
      },
      "provider": {
        "name": "Microsoft Learn",
        "domain": "microsoft.com",
        "images": [
          {
            "url": "https://smartableai.github.io/microsoft-azure/assets/images/organizations/microsoft.com-50x50.jpg",
            "width": 50,
            "height": 50,
            "isCached": false
          }
        ]
      },
      "levels": [
        "Beginner"
      ],
      "heat": 51,
      "content": "\r\n",
      "type": "course",
      "price": "Free",
      "topics": [
        "Azure",
        "IoT",
        "Storage",
        "Databases"
      ]
    },
    {
      "path": "_learning/courses/microsoft-learn-introduction-to-github-vs-code.md",
      "title": "Introduction to GitHub in Visual Studio Code",
      "excerpt": "Learn to use the GitHub integration in Visual Studio Code, including authentication, publishing repos and viewing your repo timeline",
      "sourceUrl": "https://smartableai.github.io/microsoft-azure/api/learning/courses/microsoft-learn-introduction-to-github-vs-code/index.json",
      "webUrl": "https://docs.microsoft.com/en-us/learn/modules/introduction-to-github-visual-studio-code/",
      "length": "PT22M",
      "ratings": {
        "count": 39,
        "average": 4.820513
      },
      "provider": {
        "name": "Microsoft Learn",
        "domain": "microsoft.com",
        "images": [
          {
            "url": "https://smartableai.github.io/microsoft-azure/assets/images/organizations/microsoft.com-50x50.jpg",
            "width": 50,
            "height": 50,
            "isCached": false
          }
        ]
      },
      "levels": [
        "Beginner"
      ],
      "heat": 51,
      "images": [
        {
          "url": "https://docs.microsoft.com/learn/achievements/github/introduction-to-github-social.png",
          "width": 640,
          "height": 320,
          "isCached": true
        }
      ],
      "content": "\r\n",
      "type": "course",
      "price": "Free",
      "topics": [
        "Azure",
        "Developer tools"
      ]
    },
    {
      "path": "_learning/courses/microsoft-learn-introduction-to-github.md",
      "title": "Introduction to GitHub",
      "excerpt": "Learn to use key GitHub features, including issues, notifications, branches, commits, and pull requests.",
      "sourceUrl": "https://smartableai.github.io/microsoft-azure/api/learning/courses/microsoft-learn-introduction-to-github/index.json",
      "webUrl": "https://docs.microsoft.com/en-us/learn/modules/introduction-to-github/",
      "length": "PT1H12M",
      "ratings": {
        "count": 776,
        "average": 4.7332473
      },
      "provider": {
        "name": "Microsoft Learn",
        "domain": "microsoft.com",
        "images": [
          {
            "url": "https://smartableai.github.io/microsoft-azure/assets/images/organizations/microsoft.com-50x50.jpg",
            "width": 50,
            "height": 50,
            "isCached": false
          }
        ]
      },
      "levels": [
        "Beginner"
      ],
      "heat": 51,
      "images": [
        {
          "url": "https://docs.microsoft.com/learn/achievements/github/introduction-to-github-social.png",
          "width": 640,
          "height": 320,
          "isCached": true
        }
      ],
      "content": "\r\n",
      "type": "course",
      "price": "Free",
      "topics": [
        "Azure"
      ]
    },
    {
      "path": "_learning/courses/microsoft-learn-learn-data-science-method.md",
      "title": "Learn the data science method",
      "excerpt": "Learn about the history and motivation behind data science",
      "sourceUrl": "https://smartableai.github.io/microsoft-azure/api/learning/courses/microsoft-learn-learn-data-science-method/index.json",
      "webUrl": "https://docs.microsoft.com/en-us/learn/modules/learn-data-science-method/",
      "length": "PT34M",
      "ratings": {
        "count": 537,
        "average": 4.718808
      },
      "provider": {
        "name": "Microsoft Learn",
        "domain": "microsoft.com",
        "images": [
          {
            "url": "https://smartableai.github.io/microsoft-azure/assets/images/organizations/microsoft.com-50x50.jpg",
            "width": 50,
            "height": 50,
            "isCached": false
          }
        ]
      },
      "levels": [
        "Beginner"
      ],
      "heat": 51,
      "images": [
        {
          "url": "https://docs.microsoft.com/learn/achievements/student-evangelism/learn-data-science-method-social.png",
          "width": 640,
          "height": 320,
          "isCached": true
        }
      ],
      "content": "\r\n",
      "type": "course",
      "price": "Free",
      "topics": [
        "Azure"
      ]
    },
    {
      "path": "_learning/courses/microsoft-learn-manage-costs-partner-cost-management.md",
      "title": "Configure and manage costs as a Microsoft partner by using Azure Cost Management",
      "excerpt": "Learn how to reconcile your bill and analyze costs across your customers and resources by using Azure Cost Management as a partner.",
      "sourceUrl": "https://smartableai.github.io/microsoft-azure/api/learning/courses/microsoft-learn-manage-costs-partner-cost-management/index.json",
      "webUrl": "https://docs.microsoft.com/en-us/learn/modules/manage-costs-partner-cost-management/",
      "length": "PT34M",
      "ratings": {
        "count": 35,
        "average": 4.8
      },
      "provider": {
        "name": "Microsoft Learn",
        "domain": "microsoft.com",
        "images": [
          {
            "url": "https://smartableai.github.io/microsoft-azure/assets/images/organizations/microsoft.com-50x50.jpg",
            "width": 50,
            "height": 50,
            "isCached": false
          }
        ]
      },
      "levels": [
        "Beginner"
      ],
      "heat": 51,
      "images": [
        {
          "url": "https://docs.microsoft.com/learn/achievements/manage-costs-partner-cost-management-social.png",
          "width": 640,
          "height": 320,
          "isCached": true
        }
      ],
      "content": "\r\n",
      "type": "course",
      "price": "Free",
      "topics": [
        "Azure",
        "Management Tools"
      ]
    },
    {
      "path": "_learning/courses/microsoft-learn-manage-language-understanding-intelligent-service-apps.md",
      "title": "Manage your Language Understanding Intelligent Service (LUIS) Apps",
      "excerpt": "Learn to manage LUIS apps through versioning, key management, handling data, and improving predictions.",
      "sourceUrl": "https://smartableai.github.io/microsoft-azure/api/learning/courses/microsoft-learn-manage-language-understanding-intelligent-service-apps/index.json",
      "webUrl": "https://docs.microsoft.com/en-us/learn/modules/manage-language-understanding-intelligent-service-apps/",
      "length": "PT24M",
      "ratings": {
        "count": 60,
        "average": 4.7833333
      },
      "provider": {
        "name": "Microsoft Learn",
        "domain": "microsoft.com",
        "images": [
          {
            "url": "https://smartableai.github.io/microsoft-azure/assets/images/organizations/microsoft.com-50x50.jpg",
            "width": 50,
            "height": 50,
            "isCached": false
          }
        ]
      },
      "levels": [
        "Intermediate"
      ],
      "heat": 51,
      "images": [
        {
          "url": "https://docs.microsoft.com/learn/achievements/manage-your-language-understanding-intelligent-service-luis-apps-social.png",
          "width": 642,
          "height": 321,
          "isCached": true
        }
      ],
      "content": "\r\n",
      "type": "course",
      "price": "Free",
      "topics": [
        "Azure",
        "AI"
      ]
    },
    {
      "path": "_learning/courses/microsoft-learn-merge-conflict-resolution-github.md",
      "title": "Settle competing commits by using merge conflict resolution on GitHub",
      "excerpt": "Learn to settle overlapping commits across branches by using merge conflict resolution.",
      "sourceUrl": "https://smartableai.github.io/microsoft-azure/api/learning/courses/microsoft-learn-merge-conflict-resolution-github/index.json",
      "webUrl": "https://docs.microsoft.com/en-us/learn/modules/resolve-merge-conflicts-github/",
      "length": "PT52M",
      "ratings": {
        "count": 180,
        "average": 4.8333335
      },
      "provider": {
        "name": "Microsoft Learn",
        "domain": "microsoft.com",
        "images": [
          {
            "url": "https://smartableai.github.io/microsoft-azure/assets/images/organizations/microsoft.com-50x50.jpg",
            "width": 50,
            "height": 50,
            "isCached": false
          }
        ]
      },
      "levels": [
        "Beginner"
      ],
      "heat": 51,
      "images": [
        {
          "url": "https://docs.microsoft.com/learn/achievements/github/resolve-merge-conflicts-github-social.png",
          "width": 640,
          "height": 320,
          "isCached": true
        }
      ],
      "content": "\r\n",
      "type": "course",
      "price": "Free",
      "topics": [
        "Azure"
      ]
    },
    {
      "path": "_learning/courses/microsoft-learn-microsoft-approach-to-ai.md",
      "title": "Examine the Microsoft approach to artificial intelligence",
      "excerpt": "Learn how Microsoft creates products, services, and solutions to help organizations leverage AI. Understand how these technologies relate to business problems.",
      "sourceUrl": "https://smartableai.github.io/microsoft-azure/api/learning/courses/microsoft-learn-microsoft-approach-to-ai/index.json",
      "webUrl": "https://docs.microsoft.com/en-us/learn/modules/microsoft-approach-to-ai/",
      "length": "PT54M",
      "ratings": {
        "count": 935,
        "average": 4.722995
      },
      "provider": {
        "name": "Microsoft Learn",
        "domain": "microsoft.com",
        "images": [
          {
            "url": "https://smartableai.github.io/microsoft-azure/assets/images/organizations/microsoft.com-50x50.jpg",
            "width": 50,
            "height": 50,
            "isCached": false
          }
        ]
      },
      "levels": [
        "Beginner"
      ],
      "heat": 51,
      "images": [
        {
          "url": "https://docs.microsoft.com/learn/achievements/microsoft-approach-to-ai-social.png",
          "width": 800,
          "height": 400,
          "isCached": true
        }
      ],
      "content": "\r\n",
      "type": "course",
      "price": "Free",
      "topics": [
        "Azure",
        "AI"
      ]
    },
    {
      "path": "_learning/courses/microsoft-learn-microsoft-cloud-adoption-framework-for-azure-v1-1.md",
      "title": "Microsoft Cloud Adoption Framework for Azure",
      "excerpt": "Learn how to use the Cloud Adoption Framework to develop best practices for cloud adoption in real-world scenarios.",
      "sourceUrl": "https://smartableai.github.io/microsoft-azure/api/learning/courses/microsoft-learn-microsoft-cloud-adoption-framework-for-azure-v1-1/index.json",
      "webUrl": "https://docs.microsoft.com/en-us/learn/modules/microsoft-cloud-adoption-framework-for-azure/",
      "length": "PT50M",
      "ratings": {
        "count": 2216,
        "average": 4.741877
      },
      "provider": {
        "name": "Microsoft Learn",
        "domain": "microsoft.com",
        "images": [
          {
            "url": "https://smartableai.github.io/microsoft-azure/assets/images/organizations/microsoft.com-50x50.jpg",
            "width": 50,
            "height": 50,
            "isCached": false
          }
        ]
      },
      "levels": [
        "Beginner"
      ],
      "heat": 51,
      "images": [
        {
          "url": "https://docs.microsoft.com/learn/achievements/microsoft-cloud-adoption-framework-for-azure-social.png",
          "width": 800,
          "height": 400,
          "isCached": true
        }
      ],
      "content": "\r\n",
      "type": "course",
      "price": "Free",
      "topics": [
        "Azure"
      ]
    },
    {
      "path": "_learning/courses/microsoft-learn-microsoft-runs-on-trust.md",
      "title": "Microsoft runs on trust",
      "excerpt": "Organizations today are moving beyond the early promise of the cloud to digitally transform their businesses through faster innovation, flexible resources, and economies of scale. The Microsoft Trusted Cloud was built on the foundational principles of security, privacy, compliance, and transparency. We partner with organizations, empowering them to achieve their vision, on a trusted platform.",
      "sourceUrl": "https://smartableai.github.io/microsoft-azure/api/learning/courses/microsoft-learn-microsoft-runs-on-trust/index.json",
      "webUrl": "https://docs.microsoft.com/en-us/learn/modules/microsoft-runs-on-trust/",
      "length": "PT30M",
      "ratings": {
        "count": 5527,
        "average": 4.7410893
      },
      "provider": {
        "name": "Microsoft Learn",
        "domain": "microsoft.com",
        "images": [
          {
            "url": "https://smartableai.github.io/microsoft-azure/assets/images/organizations/microsoft.com-50x50.jpg",
            "width": 50,
            "height": 50,
            "isCached": false
          }
        ]
      },
      "levels": [
        "Beginner"
      ],
      "heat": 51,
      "images": [
        {
          "url": "https://docs.microsoft.com/learn/achievements/microsoft-runs-on-trust-social.png",
          "width": 800,
          "height": 400,
          "isCached": true
        }
      ],
      "content": "\r\n",
      "type": "course",
      "price": "Free",
      "topics": [
        "Azure"
      ]
    },
    {
      "path": "_learning/courses/microsoft-learn-monitor-data-drift-with-azure-machine-learning.md",
      "title": "Monitor data drift with Azure Machine Learning",
      "excerpt": "Changing trends in data over time can reduce the accuracy of the predictions made by a model. Monitoring for this data drift is an important way to ensure your model continues to predict accurately.",
      "sourceUrl": "https://smartableai.github.io/microsoft-azure/api/learning/courses/microsoft-learn-monitor-data-drift-with-azure-machine-learning/index.json",
      "webUrl": "https://docs.microsoft.com/en-us/learn/modules/monitor-data-drift-with-azure-machine-learning/",
      "length": "PT42M",
      "ratings": {
        "count": 320,
        "average": 4.74375
      },
      "provider": {
        "name": "Microsoft Learn",
        "domain": "microsoft.com",
        "images": [
          {
            "url": "https://smartableai.github.io/microsoft-azure/assets/images/organizations/microsoft.com-50x50.jpg",
            "width": 50,
            "height": 50,
            "isCached": false
          }
        ]
      },
      "levels": [
        "Intermediate"
      ],
      "heat": 51,
      "images": [
        {
          "url": "https://docs.microsoft.com/learn/achievements/monitor-data-drift-with-azure-machine-learning-social.png",
          "width": 640,
          "height": 320,
          "isCached": true
        }
      ],
      "content": "\r\n",
      "type": "course",
      "price": "Free",
      "topics": [
        "Azure",
        "Management Tools",
        "AI"
      ]
    },
    {
      "path": "_learning/courses/microsoft-learn-monitor-report-aad-security-events.md",
      "title": "Monitor and report on security events in Azure AD",
      "excerpt": "Keep tabs on security events in your Azure AD resources by using built-in reporting and monitoring capabilities. Respond to events as they happen, and address security risks before they become a problem.",
      "sourceUrl": "https://smartableai.github.io/microsoft-azure/api/learning/courses/microsoft-learn-monitor-report-aad-security-events/index.json",
      "webUrl": "https://docs.microsoft.com/en-us/learn/modules/monitor-report-aad-security-events/",
      "length": "PT35M",
      "ratings": {
        "count": 263,
        "average": 4.5893536
      },
      "provider": {
        "name": "Microsoft Learn",
        "domain": "microsoft.com",
        "images": [
          {
            "url": "https://smartableai.github.io/microsoft-azure/assets/images/organizations/microsoft.com-50x50.jpg",
            "width": 50,
            "height": 50,
            "isCached": false
          }
        ]
      },
      "levels": [
        "Intermediate"
      ],
      "heat": 51,
      "images": [
        {
          "url": "https://docs.microsoft.com/learn/achievements/monitor-report-aad-security-events-social.png",
          "width": 800,
          "height": 400,
          "isCached": true
        }
      ],
      "content": "\r\n",
      "type": "course",
      "price": "Free",
      "topics": [
        "Azure",
        "Identity",
        "DevOps",
        "Management Tools",
        "Security"
      ]
    },
    {
      "path": "_learning/courses/microsoft-learn-persist-data-ef-core.md",
      "title": "Persist and retrieve relational data with Entity Framework Core",
      "excerpt": "This module guides you through creating a data access project, connecting to a relational database, and writing CRUD queries.",
      "sourceUrl": "https://smartableai.github.io/microsoft-azure/api/learning/courses/microsoft-learn-persist-data-ef-core/index.json",
      "webUrl": "https://docs.microsoft.com/en-us/learn/modules/persist-data-ef-core/",
      "length": "PT1H4M",
      "ratings": {
        "count": 1043,
        "average": 4.6644297
      },
      "provider": {
        "name": "Microsoft Learn",
        "domain": "microsoft.com",
        "images": [
          {
            "url": "https://smartableai.github.io/microsoft-azure/assets/images/organizations/microsoft.com-50x50.jpg",
            "width": 50,
            "height": 50,
            "isCached": false
          }
        ]
      },
      "levels": [
        "Intermediate"
      ],
      "heat": 51,
      "images": [
        {
          "url": "https://docs.microsoft.com/learn/achievements/aspnetcore/persist-data-ef-core-social.png",
          "width": 800,
          "height": 400,
          "isCached": true
        }
      ],
      "content": "\r\n",
      "type": "course",
      "price": "Free",
      "topics": [
        "Azure",
        "DevOps",
        "Management Tools",
        "Databases"
      ]
    },
    {
      "path": "_learning/courses/microsoft-learn-prepare-for-wvd.md",
      "title": "Prepare for Windows Virtual Desktop in Microsoft Azure",
      "excerpt": "Learn how to prepare for Windows Virtual Desktop - a cloud-based virtualization solution running on Microsoft Azure. Windows Virtual Desktop is an elastically scalable service to deliver remote desktop and remote app experiences - without having to manage the underlying server infrastructure. Review the prerequisites and tools provided by Microsoft get ready to provision your first Windows Virtual Desktop host pool.",
      "sourceUrl": "https://smartableai.github.io/microsoft-azure/api/learning/courses/microsoft-learn-prepare-for-wvd/index.json",
      "webUrl": "https://docs.microsoft.com/en-us/learn/modules/m365-prepare-for-wvd/",
      "length": "PT32M",
      "ratings": {
        "count": 951,
        "average": 4.7528915
      },
      "provider": {
        "name": "Microsoft Learn",
        "domain": "microsoft.com",
        "images": [
          {
            "url": "https://smartableai.github.io/microsoft-azure/assets/images/organizations/microsoft.com-50x50.jpg",
            "width": 50,
            "height": 50,
            "isCached": false
          }
        ]
      },
      "levels": [
        "Intermediate"
      ],
      "heat": 51,
      "images": [
        {
          "url": "https://docs.microsoft.com/learn/achievements/prepare-for-windows-virtual-desktop-social.png",
          "width": 800,
          "height": 400,
          "isCached": true
        }
      ],
      "content": "\r\n",
      "type": "course",
      "price": "Free",
      "topics": [
        "Azure"
      ]
    },
    {
      "path": "_learning/courses/microsoft-learn-protect-vm-settings-with-dsc.md",
      "title": "Protect your virtual machine settings with Azure Automation State Configuration",
      "excerpt": "Learn how to protect your virtual machine settings with Azure Automation State Configuration",
      "sourceUrl": "https://smartableai.github.io/microsoft-azure/api/learning/courses/microsoft-learn-protect-vm-settings-with-dsc/index.json",
      "webUrl": "https://docs.microsoft.com/en-us/learn/modules/protect-vm-settings-with-dsc/",
      "length": "PT54M",
      "ratings": {
        "count": 1021,
        "average": 4.673849
      },
      "provider": {
        "name": "Microsoft Learn",
        "domain": "microsoft.com",
        "images": [
          {
            "url": "https://smartableai.github.io/microsoft-azure/assets/images/organizations/microsoft.com-50x50.jpg",
            "width": 50,
            "height": 50,
            "isCached": false
          }
        ]
      },
      "levels": [
        "Beginner"
      ],
      "heat": 51,
      "images": [
        {
          "url": "https://docs.microsoft.com/learn/achievements/protect-vm-settings-with-dsc-social.png",
          "width": 800,
          "height": 400,
          "isCached": true
        }
      ],
      "content": "\r\n",
      "type": "course",
      "price": "Free",
      "topics": [
        "Azure",
        "Compute",
        "Management Tools"
      ]
    },
    {
      "path": "_learning/courses/microsoft-learn-python-flask-build-ai-web-app.md",
      "title": "Build an AI web app by using Python and Flask",
      "excerpt": "Use Python, Flask, and Azure Cognitive Services to build a web app that incorporates AI",
      "sourceUrl": "https://smartableai.github.io/microsoft-azure/api/learning/courses/microsoft-learn-python-flask-build-ai-web-app/index.json",
      "webUrl": "https://docs.microsoft.com/en-us/learn/modules/python-flask-build-ai-web-app/",
      "length": "PT1H15M",
      "ratings": {
        "count": 133,
        "average": 4.5338345
      },
      "provider": {
        "name": "Microsoft Learn",
        "domain": "microsoft.com",
        "images": [
          {
            "url": "https://smartableai.github.io/microsoft-azure/assets/images/organizations/microsoft.com-50x50.jpg",
            "width": 50,
            "height": 50,
            "isCached": false
          }
        ]
      },
      "levels": [
        "Intermediate"
      ],
      "heat": 51,
      "content": "\r\n",
      "type": "course",
      "price": "Free",
      "topics": [
        "Azure",
        "AI"
      ]
    },
    {
      "path": "_learning/courses/microsoft-learn-qsharp-create-first-quantum-development-kit.md",
      "title": "Create your first Q# program by using the Quantum Development Kit",
      "excerpt": "Get started with Q# programming by building a quantum random number generator.",
      "sourceUrl": "https://smartableai.github.io/microsoft-azure/api/learning/courses/microsoft-learn-qsharp-create-first-quantum-development-kit/index.json",
      "webUrl": "https://docs.microsoft.com/en-us/learn/modules/qsharp-create-first-quantum-development-kit/",
      "length": "PT48M",
      "ratings": {
        "count": 307,
        "average": 4.8175898
      },
      "provider": {
        "name": "Microsoft Learn",
        "domain": "microsoft.com",
        "images": [
          {
            "url": "https://smartableai.github.io/microsoft-azure/assets/images/organizations/microsoft.com-50x50.jpg",
            "width": 50,
            "height": 50,
            "isCached": false
          }
        ]
      },
      "levels": [
        "Beginner"
      ],
      "heat": 51,
      "images": [
        {
          "url": "https://docs.microsoft.com/learn/achievements/quantum/qsharp-create-first-quantum-development-kit-social.png",
          "width": 640,
          "height": 320,
          "isCached": true
        }
      ],
      "content": "\r\n",
      "type": "course",
      "price": "Free",
      "topics": [
        "Azure"
      ]
    },
    {
      "path": "_learning/courses/microsoft-learn-save-money-with-azure-reserved-instances.md",
      "title": "Save money with Azure Reserved Instances",
      "excerpt": "Learn how to use plan for, buy, and manage Azure reservations to save money.",
      "sourceUrl": "https://smartableai.github.io/microsoft-azure/api/learning/courses/microsoft-learn-save-money-with-azure-reserved-instances/index.json",
      "webUrl": "https://docs.microsoft.com/en-us/learn/modules/save-money-with-azure-reserved-instances/",
      "length": "PT34M",
      "ratings": {
        "count": 119,
        "average": 4.6890755
      },
      "provider": {
        "name": "Microsoft Learn",
        "domain": "microsoft.com",
        "images": [
          {
            "url": "https://smartableai.github.io/microsoft-azure/assets/images/organizations/microsoft.com-50x50.jpg",
            "width": 50,
            "height": 50,
            "isCached": false
          }
        ]
      },
      "levels": [
        "Beginner"
      ],
      "heat": 51,
      "images": [
        {
          "url": "https://docs.microsoft.com/learn/achievements/save-money-with-azure-reservations-social.png",
          "width": 640,
          "height": 320,
          "isCached": true
        }
      ],
      "content": "\r\n",
      "type": "course",
      "price": "Free",
      "topics": [
        "Azure",
        "Management Tools"
      ]
    },
    {
      "path": "_learning/courses/microsoft-learn-search-organize-repository-history-github.md",
      "title": "Search and organize repository history by using GitHub",
      "excerpt": "Learn to search and organize repository history by using filters, blame, and cross-linking on GitHub.",
      "sourceUrl": "https://smartableai.github.io/microsoft-azure/api/learning/courses/microsoft-learn-search-organize-repository-history-github/index.json",
      "webUrl": "https://docs.microsoft.com/en-us/learn/modules/search-organize-repository-history-github/",
      "length": "PT38M",
      "ratings": {
        "count": 158,
        "average": 4.78481
      },
      "provider": {
        "name": "Microsoft Learn",
        "domain": "microsoft.com",
        "images": [
          {
            "url": "https://smartableai.github.io/microsoft-azure/assets/images/organizations/microsoft.com-50x50.jpg",
            "width": 50,
            "height": 50,
            "isCached": false
          }
        ]
      },
      "levels": [
        "Beginner"
      ],
      "heat": 51,
      "images": [
        {
          "url": "https://docs.microsoft.com/learn/achievements/github/search-organize-repository-history-github-social.png",
          "width": 640,
          "height": 320,
          "isCached": true
        }
      ],
      "content": "\r\n",
      "type": "course",
      "price": "Free",
      "topics": [
        "Azure"
      ]
    },
    {
      "path": "_learning/courses/microsoft-learn-stage-deploy-app-service-deployment-slots.md",
      "title": "Stage a web app deployment for testing and rollback by using App Service deployment slots",
      "excerpt": "Discover the benefits of creating deployment slots to streamline deployment and roll back a web app in Azure App Service.",
      "sourceUrl": "https://smartableai.github.io/microsoft-azure/api/learning/courses/microsoft-learn-stage-deploy-app-service-deployment-slots/index.json",
      "webUrl": "https://docs.microsoft.com/en-us/learn/modules/stage-deploy-app-service-deployment-slots/",
      "length": "PT44M",
      "ratings": {
        "count": 1934,
        "average": 4.5253363
      },
      "provider": {
        "name": "Microsoft Learn",
        "domain": "microsoft.com",
        "images": [
          {
            "url": "https://smartableai.github.io/microsoft-azure/assets/images/organizations/microsoft.com-50x50.jpg",
            "width": 50,
            "height": 50,
            "isCached": false
          }
        ]
      },
      "levels": [
        "Beginner"
      ],
      "heat": 51,
      "images": [
        {
          "url": "https://docs.microsoft.com/learn/achievements/stage-deploy-app-service-deployment-slots-social.png",
          "width": 800,
          "height": 400,
          "isCached": true
        }
      ],
      "content": "\r\n",
      "type": "course",
      "price": "Free",
      "topics": [
        "Azure",
        "Compute"
      ]
    }
  ],
  "nextPage": 20
}