{
  "title": "Learning Resources",
  "path": "_learning",
  "page": 24,
  "value": [
    {
      "path": "_learning/courses/microsoft-learn-hub-and-spoke-network-architecture.md",
      "title": "Centralize your core services by using hub and spoke Azure virtual network architecture",
      "excerpt": "Design a network architecture in Azure that allows for growth and flexibility, secure isolation of critical resources, low administrative overhead, and communication with on-premises network resources.",
      "sourceUrl": "https://smartableai.github.io/microsoft-azure/api/learning/courses/microsoft-learn-hub-and-spoke-network-architecture/index.json",
      "webUrl": "https://docs.microsoft.com/en-us/learn/modules/hub-and-spoke-network-architecture/",
      "length": "PT36M",
      "ratings": {
        "count": 1724,
        "average": 4.678654
      },
      "provider": {
        "name": "Microsoft Learn",
        "domain": "microsoft.com",
        "images": [
          {
            "url": "https://smartableai.github.io/microsoft-azure/assets/images/organizations/microsoft.com-50x50.jpg",
            "width": 50,
            "height": 50,
            "isCached": false
          }
        ]
      },
      "levels": [
        "Intermediate"
      ],
      "heat": 51,
      "images": [
        {
          "url": "https://docs.microsoft.com/learn/achievements/hub-and-spoke-network-architecture-social.png",
          "width": 800,
          "height": 400,
          "isCached": true
        }
      ],
      "content": "\r\n",
      "type": "course",
      "price": "Free",
      "topics": [
        "Azure",
        "Networking"
      ]
    },
    {
      "path": "_learning/courses/microsoft-learn-identify-threats-with-azure-security-center.md",
      "title": "Identify security threats with Azure Security Center",
      "excerpt": "Master securing your Azure workloads with Azure Security Center. In this module, you’ll discover how to detect and respond to threats with Azure Security Center.",
      "sourceUrl": "https://smartableai.github.io/microsoft-azure/api/learning/courses/microsoft-learn-identify-threats-with-azure-security-center/index.json",
      "webUrl": "https://docs.microsoft.com/en-us/learn/modules/identify-threats-with-azure-security-center/",
      "length": "PT43M",
      "ratings": {
        "count": 833,
        "average": 4.6938777
      },
      "provider": {
        "name": "Microsoft Learn",
        "domain": "microsoft.com",
        "images": [
          {
            "url": "https://smartableai.github.io/microsoft-azure/assets/images/organizations/microsoft.com-50x50.jpg",
            "width": 50,
            "height": 50,
            "isCached": false
          }
        ]
      },
      "levels": [
        "Beginner"
      ],
      "heat": 51,
      "images": [
        {
          "url": "https://docs.microsoft.com/learn/achievements/identify-threats-with-azure-security-center-social.png",
          "width": 800,
          "height": 400,
          "isCached": true
        }
      ],
      "content": "\r\n",
      "type": "course",
      "price": "Free",
      "topics": [
        "Azure",
        "Security"
      ]
    },
    {
      "path": "_learning/courses/microsoft-learn-implement-azure-backup-for-sap-workloads-azure-vms.md",
      "title": "Implement Azure Backup for SAP workloads on Azure VMs",
      "excerpt": "Implement Azure Backup for SAP workloads on Azure VMs",
      "sourceUrl": "https://smartableai.github.io/microsoft-azure/api/learning/courses/microsoft-learn-implement-azure-backup-for-sap-workloads-azure-vms/index.json",
      "webUrl": "https://docs.microsoft.com/en-us/learn/modules/implement-azure-backup-sap-workloads-azure-virtual-machines/",
      "length": "PT20M",
      "ratings": {
        "count": 39,
        "average": 4.820513
      },
      "provider": {
        "name": "Microsoft Learn",
        "domain": "microsoft.com",
        "images": [
          {
            "url": "https://smartableai.github.io/microsoft-azure/assets/images/organizations/microsoft.com-50x50.jpg",
            "width": 50,
            "height": 50,
            "isCached": false
          }
        ]
      },
      "levels": [
        "Intermediate"
      ],
      "heat": 51,
      "images": [
        {
          "url": "https://docs.microsoft.com/learn/achievements/generic-badge-social.png",
          "width": 640,
          "height": 320,
          "isCached": true
        }
      ],
      "content": "\r\n",
      "type": "course",
      "price": "Free",
      "topics": [
        "Azure",
        "Management tools"
      ]
    },
    {
      "path": "_learning/courses/microsoft-learn-implement-ci-cd-azure-devops.md",
      "title": "Implement CI/CD with Azure DevOps",
      "excerpt": "Implement CI/CD with Azure DevOps",
      "sourceUrl": "https://smartableai.github.io/microsoft-azure/api/learning/courses/microsoft-learn-implement-ci-cd-azure-devops/index.json",
      "webUrl": "https://docs.microsoft.com/en-us/learn/modules/implement-ci-cd-azure-devops/",
      "length": "PT28M",
      "ratings": {
        "count": 198,
        "average": 4.6868687
      },
      "provider": {
        "name": "Microsoft Learn",
        "domain": "microsoft.com",
        "images": [
          {
            "url": "https://smartableai.github.io/microsoft-azure/assets/images/organizations/microsoft.com-50x50.jpg",
            "width": 50,
            "height": 50,
            "isCached": false
          }
        ]
      },
      "levels": [
        "Intermediate"
      ],
      "heat": 51,
      "images": [
        {
          "url": "https://docs.microsoft.com/learn/achievements/implement-ci-cd-azure-devops-social.png",
          "width": 640,
          "height": 320,
          "isCached": true
        }
      ],
      "content": "\r\n",
      "type": "course",
      "price": "Free",
      "topics": [
        "Azure",
        "Analytics",
        "AI",
        "DevOps"
      ]
    },
    {
      "path": "_learning/courses/microsoft-learn-implement-manage-external-identities.md",
      "title": "Implement and manage external identities",
      "excerpt": "Implement and manage external identities",
      "sourceUrl": "https://smartableai.github.io/microsoft-azure/api/learning/courses/microsoft-learn-implement-manage-external-identities/index.json",
      "webUrl": "https://docs.microsoft.com/en-us/learn/modules/implement-manage-external-identities/",
      "length": "PT60M",
      "ratings": {
        "count": 353,
        "average": 4.7308784
      },
      "provider": {
        "name": "Microsoft Learn",
        "domain": "microsoft.com",
        "images": [
          {
            "url": "https://smartableai.github.io/microsoft-azure/assets/images/organizations/microsoft.com-50x50.jpg",
            "width": 50,
            "height": 50,
            "isCached": false
          }
        ]
      },
      "levels": [
        "Advanced"
      ],
      "heat": 51,
      "images": [
        {
          "url": "https://docs.microsoft.com/learn/achievements/generic-badge-social.png",
          "width": 640,
          "height": 320,
          "isCached": true
        }
      ],
      "content": "\r\n",
      "type": "course",
      "price": "Free",
      "topics": [
        "Azure",
        "Identity"
      ]
    },
    {
      "path": "_learning/courses/microsoft-learn-implement-manage-hybrid-identity.md",
      "title": "Implement and manage hybrid identity",
      "excerpt": "Implement and manage hybrid identity",
      "sourceUrl": "https://smartableai.github.io/microsoft-azure/api/learning/courses/microsoft-learn-implement-manage-hybrid-identity/index.json",
      "webUrl": "https://docs.microsoft.com/en-us/learn/modules/implement-manage-hybrid-identity/",
      "length": "PT59M",
      "ratings": {
        "count": 495,
        "average": 4.7656565
      },
      "provider": {
        "name": "Microsoft Learn",
        "domain": "microsoft.com",
        "images": [
          {
            "url": "https://smartableai.github.io/microsoft-azure/assets/images/organizations/microsoft.com-50x50.jpg",
            "width": 50,
            "height": 50,
            "isCached": false
          }
        ]
      },
      "levels": [
        "Advanced"
      ],
      "heat": 51,
      "images": [
        {
          "url": "https://docs.microsoft.com/learn/achievements/generic-badge-social.png",
          "width": 640,
          "height": 320,
          "isCached": true
        }
      ],
      "content": "\r\n",
      "type": "course",
      "price": "Free",
      "topics": [
        "Azure",
        "Identity"
      ]
    },
    {
      "path": "_learning/courses/microsoft-learn-incident-management-sentinel.md",
      "title": "Security incident management in Azure Sentinel",
      "excerpt": "Security incident management in Azure Sentinel",
      "sourceUrl": "https://smartableai.github.io/microsoft-azure/api/learning/courses/microsoft-learn-incident-management-sentinel/index.json",
      "webUrl": "https://docs.microsoft.com/en-us/learn/modules/incident-management-sentinel/",
      "length": "PT1H5M",
      "ratings": {
        "count": 122,
        "average": 4.7704916
      },
      "provider": {
        "name": "Microsoft Learn",
        "domain": "microsoft.com",
        "images": [
          {
            "url": "https://smartableai.github.io/microsoft-azure/assets/images/organizations/microsoft.com-50x50.jpg",
            "width": 50,
            "height": 50,
            "isCached": false
          }
        ]
      },
      "levels": [
        "Beginner"
      ],
      "heat": 51,
      "images": [
        {
          "url": "https://docs.microsoft.com/learn/achievements/incident-management-sentinel-social.png",
          "width": 640,
          "height": 320,
          "isCached": true
        }
      ],
      "content": "\r\n",
      "type": "course",
      "price": "Free",
      "topics": [
        "Azure",
        "Security"
      ]
    },
    {
      "path": "_learning/courses/microsoft-learn-integrate-azure-databricks-other-azure-services.md",
      "title": "Integrate Azure Databricks with other Azure services",
      "excerpt": "Integrate Azure Databricks with other Azure services",
      "sourceUrl": "https://smartableai.github.io/microsoft-azure/api/learning/courses/microsoft-learn-integrate-azure-databricks-other-azure-services/index.json",
      "webUrl": "https://docs.microsoft.com/en-us/learn/modules/integrate-azure-databricks-other-azure-services/",
      "length": "PT33M",
      "ratings": {
        "count": 173,
        "average": 4.5317917
      },
      "provider": {
        "name": "Microsoft Learn",
        "domain": "microsoft.com",
        "images": [
          {
            "url": "https://smartableai.github.io/microsoft-azure/assets/images/organizations/microsoft.com-50x50.jpg",
            "width": 50,
            "height": 50,
            "isCached": false
          }
        ]
      },
      "levels": [
        "Intermediate"
      ],
      "heat": 51,
      "images": [
        {
          "url": "https://docs.microsoft.com/learn/achievements/integrate-azure-databricks-other-azure-services-social.png",
          "width": 640,
          "height": 320,
          "isCached": true
        }
      ],
      "content": "\r\n",
      "type": "course",
      "price": "Free",
      "topics": [
        "Azure",
        "Analytics",
        "AI"
      ]
    },
    {
      "path": "_learning/courses/microsoft-learn-intro-machine-learning.md",
      "title": "Introduction to PyTorch",
      "excerpt": "Learn how to build machine learning models with PyTorch",
      "sourceUrl": "https://smartableai.github.io/microsoft-azure/api/learning/courses/microsoft-learn-intro-machine-learning/index.json",
      "webUrl": "https://docs.microsoft.com/en-us/learn/modules/intro-machine-learning-pytorch/",
      "length": "PT1H30M",
      "ratings": {
        "count": 86,
        "average": 4.7325583
      },
      "provider": {
        "name": "Microsoft Learn",
        "domain": "microsoft.com",
        "images": [
          {
            "url": "https://smartableai.github.io/microsoft-azure/assets/images/organizations/microsoft.com-50x50.jpg",
            "width": 50,
            "height": 50,
            "isCached": false
          }
        ]
      },
      "levels": [
        "Beginner"
      ],
      "heat": 51,
      "images": [
        {
          "url": "https://docs.microsoft.com/learn/achievements/generic-badge-social.png",
          "width": 640,
          "height": 320,
          "isCached": true
        }
      ],
      "content": "\r\n",
      "type": "course",
      "price": "Free",
      "topics": [
        "Azure"
      ]
    },
    {
      "path": "_learning/courses/microsoft-learn-intro-to-azure-data-factory.md",
      "title": "Introduction to Azure Data Factory",
      "excerpt": "Evaluate whether Azure Data Factory can help you integrate your data sources. Describe how Azure Data Factory can ingest data from on-premises, multiple-cloud and SaaS data sources.",
      "sourceUrl": "https://smartableai.github.io/microsoft-azure/api/learning/courses/microsoft-learn-intro-to-azure-data-factory/index.json",
      "webUrl": "https://docs.microsoft.com/en-us/learn/modules/intro-to-azure-data-factory/",
      "length": "PT35M",
      "ratings": {
        "count": 80,
        "average": 4.7875
      },
      "provider": {
        "name": "Microsoft Learn",
        "domain": "microsoft.com",
        "images": [
          {
            "url": "https://smartableai.github.io/microsoft-azure/assets/images/organizations/microsoft.com-50x50.jpg",
            "width": 50,
            "height": 50,
            "isCached": false
          }
        ]
      },
      "levels": [
        "Beginner"
      ],
      "heat": 51,
      "images": [
        {
          "url": "https://docs.microsoft.com/learn/achievements/intro-to-azure-data-factory-social.png",
          "width": 641,
          "height": 321,
          "isCached": true
        }
      ],
      "content": "\r\n",
      "type": "course",
      "price": "Free",
      "topics": [
        "Azure"
      ]
    },
    {
      "path": "_learning/courses/microsoft-learn-intro-to-azure-monitor.md",
      "title": "Introduction to Azure Monitor",
      "excerpt": "Learn what Azure Monitor is and where you would use it.",
      "sourceUrl": "https://smartableai.github.io/microsoft-azure/api/learning/courses/microsoft-learn-intro-to-azure-monitor/index.json",
      "webUrl": "https://docs.microsoft.com/en-us/learn/modules/intro-to-azure-monitor/",
      "length": "PT49M",
      "ratings": {
        "count": 10,
        "average": 4.9
      },
      "provider": {
        "name": "Microsoft Learn",
        "domain": "microsoft.com",
        "images": [
          {
            "url": "https://smartableai.github.io/microsoft-azure/assets/images/organizations/microsoft.com-50x50.jpg",
            "width": 50,
            "height": 50,
            "isCached": false
          }
        ]
      },
      "levels": [
        "Beginner"
      ],
      "heat": 51,
      "content": "\r\n",
      "type": "course",
      "price": "Free",
      "topics": [
        "Azure",
        "DevOps",
        "Management Tools"
      ]
    },
    {
      "path": "_learning/courses/microsoft-learn-intro-to-azure-sentinel.md",
      "title": "Introduction to Azure Sentinel",
      "excerpt": "Get familiar with Azure Sentinel, a cloud-native, security information and event management (SIEM) service.",
      "sourceUrl": "https://smartableai.github.io/microsoft-azure/api/learning/courses/microsoft-learn-intro-to-azure-sentinel/index.json",
      "webUrl": "https://docs.microsoft.com/en-us/learn/modules/intro-to-azure-sentinel/",
      "length": "PT29M",
      "ratings": {
        "count": 775,
        "average": 4.794839
      },
      "provider": {
        "name": "Microsoft Learn",
        "domain": "microsoft.com",
        "images": [
          {
            "url": "https://smartableai.github.io/microsoft-azure/assets/images/organizations/microsoft.com-50x50.jpg",
            "width": 50,
            "height": 50,
            "isCached": false
          }
        ]
      },
      "levels": [
        "Beginner"
      ],
      "heat": 51,
      "content": "\r\n",
      "type": "course",
      "price": "Free",
      "topics": [
        "Azure",
        "Security"
      ]
    },
    {
      "path": "_learning/courses/microsoft-learn-introduction-infrastructure-code-using-bicep.md",
      "title": "Introduction to infrastructure as code using Bicep",
      "excerpt": "Describe the benefits of using infrastructure as code, Azure Resource Manager, and Bicep to quickly and confidently scale your cloud deployments.",
      "sourceUrl": "https://smartableai.github.io/microsoft-azure/api/learning/courses/microsoft-learn-introduction-infrastructure-code-using-bicep/index.json",
      "webUrl": "https://docs.microsoft.com/en-us/learn/modules/introduction-to-infrastructure-as-code-using-bicep/",
      "length": "PT40M",
      "ratings": {
        "count": 111,
        "average": 4.792793
      },
      "provider": {
        "name": "Microsoft Learn",
        "domain": "microsoft.com",
        "images": [
          {
            "url": "https://smartableai.github.io/microsoft-azure/assets/images/organizations/microsoft.com-50x50.jpg",
            "width": 50,
            "height": 50,
            "isCached": false
          }
        ]
      },
      "levels": [
        "Beginner"
      ],
      "heat": 51,
      "images": [
        {
          "url": "https://docs.microsoft.com/learn/achievements/bicep/introduction-infrastructure-code-using-bicep-social.png",
          "width": 1280,
          "height": 641,
          "isCached": true
        }
      ],
      "content": "\r\n",
      "type": "course",
      "price": "Free",
      "topics": [
        "Azure",
        "Management Tools"
      ]
    },
    {
      "path": "_learning/courses/microsoft-learn-introduction-open-source-analytics-offering.md",
      "title": "Introduction to the Open source Analytics Offering",
      "excerpt": "Introduction to the Open source Analytics Offering",
      "sourceUrl": "https://smartableai.github.io/microsoft-azure/api/learning/courses/microsoft-learn-introduction-open-source-analytics-offering/index.json",
      "webUrl": "https://docs.microsoft.com/en-us/learn/modules/intro-open-source-analytics-offering/",
      "length": "PT31M",
      "ratings": {
        "count": 253,
        "average": 4.644269
      },
      "provider": {
        "name": "Microsoft Learn",
        "domain": "microsoft.com",
        "images": [
          {
            "url": "https://smartableai.github.io/microsoft-azure/assets/images/organizations/microsoft.com-50x50.jpg",
            "width": 50,
            "height": 50,
            "isCached": false
          }
        ]
      },
      "levels": [
        "Beginner"
      ],
      "heat": 51,
      "images": [
        {
          "url": "https://docs.microsoft.com/learn/achievements/introduction-to-the-open-source-analytics-offering-social.png",
          "width": 800,
          "height": 400,
          "isCached": true
        }
      ],
      "content": "\r\n",
      "type": "course",
      "price": "Free",
      "topics": [
        "Azure",
        "Analytics"
      ]
    },
    {
      "path": "_learning/courses/microsoft-learn-manage-enterprise-security-in-hdinsight.md",
      "title": "Manage enterprise security in HDInsight",
      "excerpt": "Manage enterprise security in HDInsight",
      "sourceUrl": "https://smartableai.github.io/microsoft-azure/api/learning/courses/microsoft-learn-manage-enterprise-security-in-hdinsight/index.json",
      "webUrl": "https://docs.microsoft.com/en-us/learn/modules/manage-enterprise-security-hdinsight/",
      "length": "PT37M",
      "ratings": {
        "count": 75,
        "average": 4.64
      },
      "provider": {
        "name": "Microsoft Learn",
        "domain": "microsoft.com",
        "images": [
          {
            "url": "https://smartableai.github.io/microsoft-azure/assets/images/organizations/microsoft.com-50x50.jpg",
            "width": 50,
            "height": 50,
            "isCached": false
          }
        ]
      },
      "levels": [
        "Intermediate"
      ],
      "heat": 51,
      "images": [
        {
          "url": "https://docs.microsoft.com/learn/achievements/manage-enterprise-security-in-hdinsight-social.png",
          "width": 800,
          "height": 400,
          "isCached": true
        }
      ],
      "content": "\r\n",
      "type": "course",
      "price": "Free",
      "topics": [
        "Azure",
        "Analytics",
        "Security"
      ]
    },
    {
      "path": "_learning/courses/microsoft-learn-manage-monitor-data-warehouse-activities-azure-synapse-analytics.md",
      "title": "Manage and monitor data warehouse activities in Azure Synapse Analytics",
      "excerpt": "Manage and monitor data warehouse activities in Azure Synapse Analytics",
      "sourceUrl": "https://smartableai.github.io/microsoft-azure/api/learning/courses/microsoft-learn-manage-monitor-data-warehouse-activities-azure-synapse-analytics/index.json",
      "webUrl": "https://docs.microsoft.com/en-us/learn/modules/manage-monitor-data-warehouse-activities-azure-synapse-analytics/",
      "length": "PT24M",
      "ratings": {
        "count": 66,
        "average": 4.560606
      },
      "provider": {
        "name": "Microsoft Learn",
        "domain": "microsoft.com",
        "images": [
          {
            "url": "https://smartableai.github.io/microsoft-azure/assets/images/organizations/microsoft.com-50x50.jpg",
            "width": 50,
            "height": 50,
            "isCached": false
          }
        ]
      },
      "levels": [
        "Beginner"
      ],
      "heat": 51,
      "images": [
        {
          "url": "https://docs.microsoft.com/learn/achievements/manage-monitor-data-warehouse-activities-social.png",
          "width": 640,
          "height": 320,
          "isCached": true
        }
      ],
      "content": "\r\n",
      "type": "course",
      "price": "Free",
      "topics": [
        "Azure",
        "Analytics"
      ]
    },
    {
      "path": "_learning/courses/microsoft-learn-microsoft-approach-to-ai.md",
      "title": "Examine the Microsoft approach to artificial intelligence",
      "excerpt": "Learn how Microsoft creates products, services, and solutions to help organizations leverage AI. Understand how these technologies relate to business problems.",
      "sourceUrl": "https://smartableai.github.io/microsoft-azure/api/learning/courses/microsoft-learn-microsoft-approach-to-ai/index.json",
      "webUrl": "https://docs.microsoft.com/en-us/learn/modules/microsoft-approach-to-ai/",
      "length": "PT54M",
      "ratings": {
        "count": 1061,
        "average": 4.7012253
      },
      "provider": {
        "name": "Microsoft Learn",
        "domain": "microsoft.com",
        "images": [
          {
            "url": "https://smartableai.github.io/microsoft-azure/assets/images/organizations/microsoft.com-50x50.jpg",
            "width": 50,
            "height": 50,
            "isCached": false
          }
        ]
      },
      "levels": [
        "Beginner"
      ],
      "heat": 51,
      "images": [
        {
          "url": "https://docs.microsoft.com/learn/achievements/microsoft-approach-to-ai-social.png",
          "width": 800,
          "height": 400,
          "isCached": true
        }
      ],
      "content": "\r\n",
      "type": "course",
      "price": "Free",
      "topics": [
        "Azure",
        "AI"
      ]
    },
    {
      "path": "_learning/courses/microsoft-learn-migrate-sql-server-relational-data.md",
      "title": "Migrate your relational data stored in SQL Server to Azure SQL Database",
      "excerpt": "Plan and implement the migration of relational data from SQL Server to Azure SQL Database. Select the appropriate migration strategy for your database, and then use Data Migration Assistant to do the assessment and the migration.",
      "sourceUrl": "https://smartableai.github.io/microsoft-azure/api/learning/courses/microsoft-learn-migrate-sql-server-relational-data/index.json",
      "webUrl": "https://docs.microsoft.com/en-us/learn/modules/migrate-sql-server-relational-data/",
      "length": "PT1H24M",
      "ratings": {
        "count": 1574,
        "average": 4.489835
      },
      "provider": {
        "name": "Microsoft Learn",
        "domain": "microsoft.com",
        "images": [
          {
            "url": "https://smartableai.github.io/microsoft-azure/assets/images/organizations/microsoft.com-50x50.jpg",
            "width": 50,
            "height": 50,
            "isCached": false
          }
        ]
      },
      "levels": [
        "Beginner"
      ],
      "heat": 51,
      "content": "\r\n",
      "type": "course",
      "price": "Free",
      "topics": [
        "Azure",
        "Databases",
        "Migration",
        "Management Tools"
      ]
    },
    {
      "path": "_learning/courses/microsoft-learn-migrate-vmware-workloads-on-premises-azure-vmware-solution.md",
      "title": "Migrate VMware workloads on-premises to Azure VMware Solution",
      "excerpt": "Learn how to migrate virtual machines from an on-premises VMware environment to Azure VMware Solution by using VMware HCX.",
      "sourceUrl": "https://smartableai.github.io/microsoft-azure/api/learning/courses/microsoft-learn-migrate-vmware-workloads-on-premises-azure-vmware-solution/index.json",
      "webUrl": "https://docs.microsoft.com/en-us/learn/modules/migrate-vmware-workloads-on-premises-azure-vmware-solution/",
      "length": "PT53M",
      "ratings": {
        "count": 7,
        "average": 5.0
      },
      "provider": {
        "name": "Microsoft Learn",
        "domain": "microsoft.com",
        "images": [
          {
            "url": "https://smartableai.github.io/microsoft-azure/assets/images/organizations/microsoft.com-50x50.jpg",
            "width": 50,
            "height": 50,
            "isCached": false
          }
        ]
      },
      "levels": [
        "Intermediate"
      ],
      "heat": 51,
      "images": [
        {
          "url": "https://docs.microsoft.com/learn/achievements/migrate-vmware-workloads-on-premises-azure-vmware-solution-social.png",
          "width": 641,
          "height": 321,
          "isCached": true
        }
      ],
      "content": "\r\n",
      "type": "course",
      "price": "Free",
      "topics": [
        "Azure"
      ]
    },
    {
      "path": "_learning/courses/microsoft-learn-monitor-models-with-azure-machine-learning.md",
      "title": "Monitor models with Azure Machine Learning",
      "excerpt": "After a machine learning model has been deployed into production, it's important to understand how it is being used by capturing and viewing telemetry.",
      "sourceUrl": "https://smartableai.github.io/microsoft-azure/api/learning/courses/microsoft-learn-monitor-models-with-azure-machine-learning/index.json",
      "webUrl": "https://docs.microsoft.com/en-us/learn/modules/monitor-models-with-azure-machine-learning/",
      "length": "PT39M",
      "ratings": {
        "count": 580,
        "average": 4.7482758
      },
      "provider": {
        "name": "Microsoft Learn",
        "domain": "microsoft.com",
        "images": [
          {
            "url": "https://smartableai.github.io/microsoft-azure/assets/images/organizations/microsoft.com-50x50.jpg",
            "width": 50,
            "height": 50,
            "isCached": false
          }
        ]
      },
      "levels": [
        "Intermediate"
      ],
      "heat": 51,
      "images": [
        {
          "url": "https://docs.microsoft.com/learn/achievements/monitor-models-with-azure-machine-learning-social.png",
          "width": 640,
          "height": 320,
          "isCached": true
        }
      ],
      "content": "\r\n",
      "type": "course",
      "price": "Free",
      "topics": [
        "Azure",
        "Management Tools",
        "AI"
      ]
    },
    {
      "path": "_learning/courses/microsoft-learn-optimize-costs-data-analysis-powerbi.md",
      "title": "Optimize Azure costs with data analysis in Power BI",
      "excerpt": "Use Power BI to understand where your money is being spent in Azure so you can help your organization to optimize its costs.",
      "sourceUrl": "https://smartableai.github.io/microsoft-azure/api/learning/courses/microsoft-learn-optimize-costs-data-analysis-powerbi/index.json",
      "webUrl": "https://docs.microsoft.com/en-us/learn/modules/optimize-costs-data-analysis-powerbi/",
      "length": "PT27M",
      "ratings": {
        "count": 50,
        "average": 4.78
      },
      "provider": {
        "name": "Microsoft Learn",
        "domain": "microsoft.com",
        "images": [
          {
            "url": "https://smartableai.github.io/microsoft-azure/assets/images/organizations/microsoft.com-50x50.jpg",
            "width": 50,
            "height": 50,
            "isCached": false
          }
        ]
      },
      "levels": [
        "Beginner"
      ],
      "heat": 51,
      "images": [
        {
          "url": "https://docs.microsoft.com/learn/achievements/optimize-costs-data-analysis-powerbi-social.png",
          "width": 640,
          "height": 320,
          "isCached": true
        }
      ],
      "content": "\r\n",
      "type": "course",
      "price": "Free",
      "topics": [
        "Azure",
        "Management Tools"
      ]
    },
    {
      "path": "_learning/courses/microsoft-learn-optimize-web-app-with-redis.md",
      "title": "Optimize your web applications by caching read-only data with Redis",
      "excerpt": "Use Redis caching in Azure to reduce the load on databases. Apply different caching architectures to support larger loads in distributed and high-volume environments.",
      "sourceUrl": "https://smartableai.github.io/microsoft-azure/api/learning/courses/microsoft-learn-optimize-web-app-with-redis/index.json",
      "webUrl": "https://docs.microsoft.com/en-us/learn/modules/optimize-your-web-apps-with-redis/",
      "length": "PT55M",
      "ratings": {
        "count": 436,
        "average": 4.7568808
      },
      "provider": {
        "name": "Microsoft Learn",
        "domain": "microsoft.com",
        "images": [
          {
            "url": "https://smartableai.github.io/microsoft-azure/assets/images/organizations/microsoft.com-50x50.jpg",
            "width": 50,
            "height": 50,
            "isCached": false
          }
        ]
      },
      "levels": [
        "Beginner"
      ],
      "heat": 51,
      "content": "\r\n",
      "type": "course",
      "price": "Free",
      "topics": [
        "Azure"
      ]
    },
    {
      "path": "_learning/courses/microsoft-learn-perform-advanced-streaming-data-transformations-with-spark-kafka.md",
      "title": "Perform advanced streaming data transformations with Apache Spark and Kafka in Azure HDInsight",
      "excerpt": "Perform advanced streaming data transformations with Apache Spark and Kafka in Azure HDInsight",
      "sourceUrl": "https://smartableai.github.io/microsoft-azure/api/learning/courses/microsoft-learn-perform-advanced-streaming-data-transformations-with-spark-kafka/index.json",
      "webUrl": "https://docs.microsoft.com/en-us/learn/modules/perform-advanced-streaming-data-transformations-with-spark-kafka/",
      "length": "PT46M",
      "ratings": {
        "count": 89,
        "average": 4.4606743
      },
      "provider": {
        "name": "Microsoft Learn",
        "domain": "microsoft.com",
        "images": [
          {
            "url": "https://smartableai.github.io/microsoft-azure/assets/images/organizations/microsoft.com-50x50.jpg",
            "width": 50,
            "height": 50,
            "isCached": false
          }
        ]
      },
      "levels": [
        "Intermediate"
      ],
      "heat": 51,
      "images": [
        {
          "url": "https://docs.microsoft.com/learn/achievements/perform-advanced-streaming-data-transformations-social.png",
          "width": 800,
          "height": 400,
          "isCached": true
        }
      ],
      "content": "\r\n",
      "type": "course",
      "price": "Free",
      "topics": [
        "Azure",
        "Analytics"
      ]
    },
    {
      "path": "_learning/courses/microsoft-learn-perform-machine-learning-with-azure-databricks.md",
      "title": "Perform machine learning with Azure Databricks",
      "excerpt": "Perform machine learning with Azure Databricks",
      "sourceUrl": "https://smartableai.github.io/microsoft-azure/api/learning/courses/microsoft-learn-perform-machine-learning-with-azure-databricks/index.json",
      "webUrl": "https://docs.microsoft.com/en-us/learn/modules/perform-machine-learning-with-azure-databricks/",
      "length": "PT59M",
      "ratings": {
        "count": 91,
        "average": 4.626374
      },
      "provider": {
        "name": "Microsoft Learn",
        "domain": "microsoft.com",
        "images": [
          {
            "url": "https://smartableai.github.io/microsoft-azure/assets/images/organizations/microsoft.com-50x50.jpg",
            "width": 50,
            "height": 50,
            "isCached": false
          }
        ]
      },
      "levels": [
        "Intermediate"
      ],
      "heat": 51,
      "images": [
        {
          "url": "https://docs.microsoft.com/learn/achievements/perform-machine-learning-with-azure-databricks-social.png",
          "width": 640,
          "height": 320,
          "isCached": true
        }
      ],
      "content": "\r\n",
      "type": "course",
      "price": "Free",
      "topics": [
        "Azure",
        "Analytics",
        "AI"
      ]
    },
    {
      "path": "_learning/courses/microsoft-learn-perform-zero-etl-analytics-hdinsight-interactive-query.md",
      "title": "Perform Zero ETL analytics with HDInsight Interactive Query",
      "excerpt": "Perform Zero ETL analytics with HDInsight Interactive Query",
      "sourceUrl": "https://smartableai.github.io/microsoft-azure/api/learning/courses/microsoft-learn-perform-zero-etl-analytics-hdinsight-interactive-query/index.json",
      "webUrl": "https://docs.microsoft.com/en-us/learn/modules/perform-zero-etl-analytics-hdinsight-interactive-query/",
      "length": "PT56M",
      "ratings": {
        "count": 118,
        "average": 4.6525426
      },
      "provider": {
        "name": "Microsoft Learn",
        "domain": "microsoft.com",
        "images": [
          {
            "url": "https://smartableai.github.io/microsoft-azure/assets/images/organizations/microsoft.com-50x50.jpg",
            "width": 50,
            "height": 50,
            "isCached": false
          }
        ]
      },
      "levels": [
        "Beginner"
      ],
      "heat": 51,
      "images": [
        {
          "url": "https://docs.microsoft.com/learn/achievements/perform-zero-etl-analytics-with-hdinsights-interactive-query-social.png",
          "width": 800,
          "height": 400,
          "isCached": true
        }
      ],
      "content": "\r\n",
      "type": "course",
      "price": "Free",
      "topics": [
        "Azure",
        "Analytics"
      ]
    },
    {
      "path": "_learning/courses/microsoft-learn-planning-implementing-sap-solutions-azure.md",
      "title": "Planning for implementing SAP solutions on Azure",
      "excerpt": "Planning for implementing SAP solutions on Azure",
      "sourceUrl": "https://smartableai.github.io/microsoft-azure/api/learning/courses/microsoft-learn-planning-implementing-sap-solutions-azure/index.json",
      "webUrl": "https://docs.microsoft.com/en-us/learn/modules/plan-implement-sap-solutions/",
      "length": "PT1H21M",
      "ratings": {
        "count": 312,
        "average": 4.801282
      },
      "provider": {
        "name": "Microsoft Learn",
        "domain": "microsoft.com",
        "images": [
          {
            "url": "https://smartableai.github.io/microsoft-azure/assets/images/organizations/microsoft.com-50x50.jpg",
            "width": 50,
            "height": 50,
            "isCached": false
          }
        ]
      },
      "levels": [
        "Advanced"
      ],
      "heat": 51,
      "images": [
        {
          "url": "https://docs.microsoft.com/learn/achievements/planning-implementing-sap-solutions-azure-social.png",
          "width": 800,
          "height": 400,
          "isCached": true
        }
      ],
      "content": "\r\n",
      "type": "course",
      "price": "Free",
      "topics": [
        "Azure"
      ]
    },
    {
      "path": "_learning/courses/microsoft-learn-provision-azure-sql-db.md",
      "title": "Provision an Azure SQL database to store application data",
      "excerpt": "Find out what makes Azure SQL Database a good choice for your relational database, how to create the database from the portal and connect with Azure Cloud Shell.",
      "sourceUrl": "https://smartableai.github.io/microsoft-azure/api/learning/courses/microsoft-learn-provision-azure-sql-db/index.json",
      "webUrl": "https://docs.microsoft.com/en-us/learn/modules/provision-azure-sql-db/",
      "length": "PT50M",
      "ratings": {
        "count": 5602,
        "average": 4.6669044
      },
      "provider": {
        "name": "Microsoft Learn",
        "domain": "microsoft.com",
        "images": [
          {
            "url": "https://smartableai.github.io/microsoft-azure/assets/images/organizations/microsoft.com-50x50.jpg",
            "width": 50,
            "height": 50,
            "isCached": false
          }
        ]
      },
      "levels": [
        "Beginner"
      ],
      "heat": 51,
      "content": "\r\n",
      "type": "course",
      "price": "Free",
      "topics": [
        "Azure",
        "Databases",
        "Management Tools"
      ]
    },
    {
      "path": "_learning/courses/microsoft-learn-register-and-deploy-model-with-amls.md",
      "title": "Deploy real-time machine learning services with Azure Machine Learning",
      "excerpt": "Learn how to register and deploy ML models as real-rim services with the Azure Machine Learning service.",
      "sourceUrl": "https://smartableai.github.io/microsoft-azure/api/learning/courses/microsoft-learn-register-and-deploy-model-with-amls/index.json",
      "webUrl": "https://docs.microsoft.com/en-us/learn/modules/register-and-deploy-model-with-amls/",
      "length": "PT40M",
      "ratings": {
        "count": 1439,
        "average": 4.654621
      },
      "provider": {
        "name": "Microsoft Learn",
        "domain": "microsoft.com",
        "images": [
          {
            "url": "https://smartableai.github.io/microsoft-azure/assets/images/organizations/microsoft.com-50x50.jpg",
            "width": 50,
            "height": 50,
            "isCached": false
          }
        ]
      },
      "levels": [
        "Beginner"
      ],
      "heat": 51,
      "images": [
        {
          "url": "https://docs.microsoft.com/learn/achievements/register-and-deploy-model-with-amls-badge-social.png",
          "width": 800,
          "height": 400,
          "isCached": true
        }
      ],
      "content": "\r\n",
      "type": "course",
      "price": "Free",
      "topics": [
        "Azure",
        "AI"
      ]
    },
    {
      "path": "_learning/courses/microsoft-learn-run-petabyte-level-oss-nosql-databases-with-hdinsight-hbase.md",
      "title": "Run Petabyte level OSS NoSQL databases with HDInsight HBase",
      "excerpt": "Run Petabyte level OSS NoSQL databases with HDInsight HBase",
      "sourceUrl": "https://smartableai.github.io/microsoft-azure/api/learning/courses/microsoft-learn-run-petabyte-level-oss-nosql-databases-with-hdinsight-hbase/index.json",
      "webUrl": "https://docs.microsoft.com/en-us/learn/modules/run-petabyte-level-oss-nosql-databases-hdinsight-hbase/",
      "length": "PT30M",
      "ratings": {
        "count": 33,
        "average": 4.6363635
      },
      "provider": {
        "name": "Microsoft Learn",
        "domain": "microsoft.com",
        "images": [
          {
            "url": "https://smartableai.github.io/microsoft-azure/assets/images/organizations/microsoft.com-50x50.jpg",
            "width": 50,
            "height": 50,
            "isCached": false
          }
        ]
      },
      "levels": [
        "Beginner"
      ],
      "heat": 51,
      "images": [
        {
          "url": "https://docs.microsoft.com/learn/achievements/run-petabyte-level-oss-nosql-databases-with-hdinsight-hbase-social.png",
          "width": 800,
          "height": 400,
          "isCached": true
        }
      ],
      "content": "\r\n",
      "type": "course",
      "price": "Free",
      "topics": [
        "Azure",
        "Analytics"
      ]
    },
    {
      "path": "_learning/courses/microsoft-learn-run-web-app-background-task-with-webjobs.md",
      "title": "Run a background task in an App Service Web App with WebJobs",
      "excerpt": "In this module, we'll guide you through creating a WebJob in the same project as an existing Web App and automating tasks with WebJobs.",
      "sourceUrl": "https://smartableai.github.io/microsoft-azure/api/learning/courses/microsoft-learn-run-web-app-background-task-with-webjobs/index.json",
      "webUrl": "https://docs.microsoft.com/en-us/learn/modules/run-web-app-background-task-with-webjobs/",
      "length": "PT39M",
      "ratings": {
        "count": 889,
        "average": 4.4015746
      },
      "provider": {
        "name": "Microsoft Learn",
        "domain": "microsoft.com",
        "images": [
          {
            "url": "https://smartableai.github.io/microsoft-azure/assets/images/organizations/microsoft.com-50x50.jpg",
            "width": 50,
            "height": 50,
            "isCached": false
          }
        ]
      },
      "levels": [
        "Beginner"
      ],
      "heat": 51,
      "images": [
        {
          "url": "https://docs.microsoft.com/learn/achievements/run-web-app-background-task-with-webjobs-social.png",
          "width": 800,
          "height": 400,
          "isCached": true
        }
      ],
      "content": "\r\n",
      "type": "course",
      "price": "Free",
      "topics": [
        "Azure",
        "Compute"
      ]
    }
  ],
  "nextPage": 25
}